osumix/__init__.py
osumix/_pydub_util.py
osumix/audio/drum-hitclap.wav
osumix/audio/drum-hitfinish.wav
osumix/audio/drum-hitnormal.wav
osumix/audio/drum-hitwhistle.wav
osumix/audio/drum-sliderslide.wav
osumix/audio/drum-slidertick.wav
osumix/audio/drum-sliderwhistle.wav
osumix/audio/normal-hitclap.wav
osumix/audio/normal-hitfinish.wav
osumix/audio/normal-hitnormal.wav
osumix/audio/normal-hitwhistle.wav
osumix/audio/normal-sliderslide.wav
osumix/audio/normal-slidertick.wav
osumix/audio/normal-sliderwhistle.wav
osumix/audio/soft-hitclap.wav
osumix/audio/soft-hitfinish.wav
osumix/audio/soft-hitnormal.wav
osumix/audio/soft-hitwhistle.wav
osumix/audio/soft-sliderslide.wav
osumix/audio/soft-slidertick.wav
osumix/audio/soft-sliderwhistle.wav
osumix/audio.py
osumix/shell.py
osumix/track.py
osumix-0.1.0.dist-info/entry_points.txt
osumix-0.1.0.dist-info/LICENSE
osumix-0.1.0.dist-info/WHEEL
osumix-0.1.0.dist-info/METADATA
osumix-0.1.0.dist-info/RECORD
